celldb-2.5-py2.7-nspkg.pth
celldb/client/__init__.py
celldb/client/client.py
celldb-2.5.dist-info/DESCRIPTION.rst
celldb-2.5.dist-info/METADATA
celldb-2.5.dist-info/RECORD
celldb-2.5.dist-info/WHEEL
celldb-2.5.dist-info/entry_points.txt
celldb-2.5.dist-info/metadata.json
celldb-2.5.dist-info/namespace_packages.txt
celldb-2.5.dist-info/top_level.txt
